pbkdf2_ctypes.py
pbkdf2_ctypes-0.99.5.dist-info/METADATA
pbkdf2_ctypes-0.99.5.dist-info/RECORD
pbkdf2_ctypes-0.99.5.dist-info/WHEEL
pbkdf2_ctypes-0.99.5.dist-info/top_level.txt
