Metadata-Version: 2.1
Name: pbkdf2-ctypes
Version: 0.99.5
Summary: Very fast implementation of pbkdf2.
Home-page: https://github.com/michele-comitini/pbkdf2_ctypes
Author: Michele Comitini
Author-email: mcm@glisco.it
License: UNKNOWN
Download-URL: https://github.com/michele-comitini/pbkdf2_ctypes/archive/0.99.5.zip
Platform: UNKNOWN
Classifier: License :: OSI Approved :: GNU Lesser General Public License v3 (LGPLv3)
Classifier: Programming Language :: Python
Classifier: Programming Language :: Python :: 2
Classifier: Programming Language :: Python :: 3
Classifier: Development Status :: 4 - Beta
Classifier: Topic :: Security :: Cryptography
